ibeacon_ble/__init__.py
ibeacon_ble/py.typed
ibeacon_ble-1.1.0.dist-info/LICENSE
ibeacon_ble-1.1.0.dist-info/METADATA
ibeacon_ble-1.1.0.dist-info/WHEEL
ibeacon_ble-1.1.0.dist-info/RECORD
